useragentutils
