Metadata-Version: 1.0
Name: useragentutils
Version: 0.1.1
Summary: Python port of the Java user-agent-utils lib
Home-page: https://github.com/krux/python-user-agent-utils
Author: Derek Brans
Author-email: dbrans@gmail.com
License: UNKNOWN
Platform: UNKNOWN
